kattis_download/__init__.py
kattis_download/main.py
kattis_problem_setup-1.0.3.dist-info/METADATA
kattis_problem_setup-1.0.3.dist-info/WHEEL
kattis_problem_setup-1.0.3.dist-info/entry_points.txt
kattis_problem_setup-1.0.3.dist-info/top_level.txt
kattis_problem_setup-1.0.3.dist-info/RECORD
