Metadata-Version: 2.1
Name: kattis-problem-setup
Version: 1.0.3
Summary: View information on Kattis problems and download sample data.
Home-page: https://github.com/bradendubois/kattis-problem-setup
Author: Braden Dubois
Author-email: braden.dubois@usask.ca
License: UNKNOWN
Keywords: kattis parsing beautifulsoup
Platform: UNKNOWN
Requires-Dist: bs4
